README.rst
setup.py
overwatch/__init__.py
overwatch/__main__.py
overwatch/server.py
overwatch.egg-info/PKG-INFO
overwatch.egg-info/SOURCES.txt
overwatch.egg-info/dependency_links.txt
overwatch.egg-info/requires.txt
overwatch.egg-info/top_level.txt
overwatch/bsoncoder/__init__.py
overwatch/bsoncoder/codec.py
overwatch/bsoncoder/network.py
overwatch/data/index.html
overwatch/data/main.css
overwatch/data/main.js
overwatch/data/libs/backbone.js
overwatch/data/libs/handlebars.js
overwatch/data/libs/jquery.js
overwatch/data/libs/moment.min.js
overwatch/data/libs/socket.io.min.js
overwatch/data/libs/underscore.js