Metadata-Version: 1.1
Name: overwatch
Version: 2.0.0
Summary: Overwatch: Python Logging Browser.
Home-page: http://andrewdunai.com/projects/overwatch/
Author: Andrew Dunai
Author-email: me@andrewdunai.com
License: UNKNOWN
Platform: unix
Classifier: Development Status :: 4 - Beta
Classifier: Environment :: Console
Classifier: Environment :: X11 Applications :: GTK
Classifier: Intended Audience :: Developers
Classifier: Intended Audience :: End Users/Desktop
Classifier: Intended Audience :: System Administrators
Classifier: License :: OSI Approved :: GNU General Public License v2 (GPLv2)
Classifier: Operating System :: POSIX :: Linux
Classifier: Programming Language :: Python :: 2.7
Classifier: Topic :: Software Development :: Debuggers
Classifier: Topic :: System :: Monitoring
